{
  "name": "studiochris/node-painter",
  "version": "0.1.4",
  "libraries": {
    "xv": "^1.1.25"
  },
  "title": "",
  "branch": "master",
  "style": {
    "name": "Swiss",
    "componentSet": {
      "nav": "nav/BasicNav",
      "header": "header/SwissHeader",
      "article": "article/SwissArticle",
      "footer": "footer/BasicFooter"
    },
    "fontFamily": "\"Helvetica Neue\", Helvetica, Arial, sans-serif",
    "heading": {
      "fontWeight": 700,
      "letterSpacing": "-0.01em"
    },
    "layout": {
      "fluid": true
    },
    "colors": {
      "text": "#000",
      "background": "#fff",
      "primary": "#05a",
      "secondary": "#444",
      "highlight": "#f30",
      "border": "#ccc",
      "muted": "#eee"
    }
  },
  "content": [
    {
      "component": "nav",
      "links": [
        {
          "href": "https://github.com/studiochris/node-painter",
          "text": "GitHub"
        }
      ]
    },
    {
      "component": "header",
      "heading": "node-painter",
      "subhead": "Node module to parse, create and edit common Corel Painter content formats",
      "children": [
        {
          "component": "ui/TweetButton",
          "text": "node-painter: Node module to parse, create and edit common Corel Painter content formats",
          "url": null
        },
        {
          "component": "ui/GithubButton",
          "user": "studiochris",
          "repo": "node-painter"
        }
      ]
    },
    {
      "component": "article",
      "metadata": {
        "source": "github.readme"
      },
      "html": "\n\n"
    },
    {
      "component": "footer",
      "links": [
        {
          "href": "https://github.com/studiochris/node-painter",
          "text": "GitHub"
        },
        {
          "href": "https://github.com/studiochris",
          "text": "studiochris"
        }
      ]
    }
  ]
}